{
  "project_info": {
    "project_number": "451316045321",
    "project_id": "cardapio-923e7",
    "storage_bucket": "cardapio-923e7.appspot.com"
  },
  "client": [
    {
      "client_info": {
        "mobilesdk_app_id": "1:451316045321:android:6dc1d8a4efbee45de04ad8",
        "android_client_info": {
          "package_name": "com.example.cardpio"
        }
      },
      "oauth_client": [],
      "api_key": [
        {
          "current_key": "AIzaSyBE4bo5Nd4UF8v8JcBgDZLvLBjshHtqh50"
        }
      ],
      "services": {
        "appinvite_service": {
          "other_platform_oauth_client": []
        }
      }
    }
  ],
  "configuration_version": "1"
 }
 
 